pyelmer/__init__.py
pyelmer/_version.py
pyelmer/elmer.py
pyelmer/elmerkw.py
pyelmer/execute.py
pyelmer/post.py
pyelmer/test/__init__.py
pyelmer/test/test_elmer.py
pyelmer/test/test_execute.py
pyelmer-1.2.1.dist-info/LICENSE
pyelmer-1.2.1.dist-info/METADATA
pyelmer-1.2.1.dist-info/WHEEL
pyelmer-1.2.1.dist-info/top_level.txt
pyelmer-1.2.1.dist-info/RECORD
