Metadata-Version: 2.1
Name: pyelmer
Version: 1.2.1
Summary: A python interface to Elmer.
Home-page: https://github.com/nemocrys/pyelmer
Author: Arved Enders-Seidlitz
Author-email: arved.enders-seidlitz@ikz-berlin.de
Classifier: Programming Language :: Python :: 3
Classifier: License :: OSI Approved :: GNU General Public License v3 or later (GPLv3+)
Classifier: Operating System :: OS Independent
Requires-Python: >=3.7
License-File: LICENSE
Requires-Dist: gmsh
Requires-Dist: pyyaml
Requires-Dist: matplotlib
Requires-Dist: numpy
Requires-Dist: objectgmsh
Requires-Dist: pandas
